{
  "files_processed": 24,
  "languages": [
    {
      "count": 4705,
      "language": "JavaScript"
    },
    {
      "count": 2827,
      "language": "Python"
    },
    {
      "count": 2665,
      "language": "Java"
    },
    {
      "count": 2262,
      "language": "Ruby"
    },
    {
      "count": 2019,
      "language": "PHP"
    },
    {
      "count": 1476,
      "language": "HTML"
    },
    {
      "count": 1222,
      "language": "C++"
    },
    {
      "count": 885,
      "language": "CSS"
    },
    {
      "count": 851,
      "language": "C"
    },
    {
      "count": 779,
      "language": "C#"
    },
    {
      "count": 576,
      "language": "Go"
    },
    {
      "count": 550,
      "language": "Shell"
    },
    {
      "count": 321,
      "language": "Objective-C"
    },
    {
      "count": 293,
      "language": "Rust"
    },
    {
      "count": 254,
      "language": "Scala"
    },
    {
      "count": 218,
      "language": "CoffeeScript"
    },
    {
      "count": 180,
      "language": "Perl"
    },
    {
      "count": 135,
      "language": "R"
    },
    {
      "count": 111,
      "language": "Haskell"
    },
    {
      "count": 101,
      "language": "Swift"
    },
    {
      "count": 93,
      "language": "Lua"
    },
    {
      "count": 86,
      "language": "Emacs Lisp"
    },
    {
      "count": 83,
      "language": "TypeScript"
    },
    {
      "count": 72,
      "language": "DM"
    },
    {
      "count": 68,
      "language": "Clojure"
    },
    {
      "count": 65,
      "language": "Makefile"
    },
    {
      "count": 63,
      "language": "VimL"
    },
    {
      "count": 55,
      "language": "Erlang"
    },
    {
      "count": 49,
      "language": "OCaml"
    },
    {
      "count": 40,
      "language": "Julia"
    },
    {
      "count": 39,
      "language": "Matlab"
    },
    {
      "count": 38,
      "language": "TeX"
    },
    {
      "count": 36,
      "language": "Puppet"
    },
    {
      "count": 36,
      "language": "Groovy"
    },
    {
      "count": 35,
      "language": "Nix"
    },
    {
      "count": 35,
      "language": "Web Ontology Language"
    },
    {
      "count": 35,
      "language": "Dart"
    },
    {
      "count": 26,
      "language": "D"
    },
    {
      "count": 24,
      "language": "Elixir"
    },
    {
      "count": 24,
      "language": "PowerShell"
    },
    {
      "count": 23,
      "language": "PLpgSQL"
    },
    {
      "count": 20,
      "language": "Eagle"
    },
    {
      "count": 20,
      "language": "ApacheConf"
    },
    {
      "count": 18,
      "language": "ActionScript"
    },
    {
      "count": 16,
      "language": "Racket"
    },
    {
      "count": 15,
      "language": "CMake"
    },
    {
      "count": 15,
      "language": "SQF"
    },
    {
      "count": 15,
      "language": "Perl6"
    },
    {
      "count": 13,
      "language": "Kotlin"
    },
    {
      "count": 13,
      "language": "PLSQL"
    },
    {
      "count": 13,
      "language": "Chapel"
    },
    {
      "count": 12,
      "language": "SQLPL"
    },
    {
      "count": 12,
      "language": "Scheme"
    },
    {
      "count": 11,
      "language": "F#"
    },
    {
      "count": 11,
      "language": "FORTRAN"
    },
    {
      "count": 11,
      "language": "Visual Basic"
    },
    {
      "count": 11,
      "language": "XSLT"
    },
    {
      "count": 10,
      "language": "Nimrod"
    },
    {
      "count": 9,
      "language": "Smalltalk"
    },
    {
      "count": 9,
      "language": "ColdFusion"
    },
    {
      "count": 8,
      "language": "Tcl"
    },
    {
      "count": 8,
      "language": "Arduino"
    },
    {
      "count": 7,
      "language": "Haxe"
    },
    {
      "count": 7,
      "language": "QML"
    },
    {
      "count": 6,
      "language": "Vala"
    },
    {
      "count": 6,
      "language": "Groff"
    },
    {
      "count": 6,
      "language": "PostScript"
    },
    {
      "count": 6,
      "language": "Augeas"
    },
    {
      "count": 6,
      "language": "Diff"
    },
    {
      "count": 6,
      "language": "GLSL"
    },
    {
      "count": 6,
      "language": "Elm"
    },
    {
      "count": 6,
      "language": "PureScript"
    },
    {
      "count": 5,
      "language": "Cucumber"
    },
    {
      "count": 5,
      "language": "LilyPond"
    },
    {
      "count": 5,
      "language": "ASP"
    },
    {
      "count": 5,
      "language": "Io"
    },
    {
      "count": 4,
      "language": "Logos"
    },
    {
      "count": 4,
      "language": "Coq"
    },
    {
      "count": 4,
      "language": "Scilab"
    },
    {
      "count": 4,
      "language": "Processing"
    },
    {
      "count": 4,
      "language": "Game Maker Language"
    },
    {
      "count": 4,
      "language": "Inno Setup"
    },
    {
      "count": 4,
      "language": "Common Lisp"
    },
    {
      "count": 4,
      "language": "Objective-C++"
    },
    {
      "count": 3,
      "language": "Handlebars"
    },
    {
      "count": 3,
      "language": "Apex"
    },
    {
      "count": 3,
      "language": "Protocol Buffer"
    },
    {
      "count": 2,
      "language": "Red"
    },
    {
      "count": 2,
      "language": "Gosu"
    },
    {
      "count": 2,
      "language": "Mathematica"
    },
    {
      "count": 2,
      "language": "XML"
    },
    {
      "count": 2,
      "language": "GAP"
    },
    {
      "count": 2,
      "language": "LLVM"
    },
    {
      "count": 2,
      "language": "Prolog"
    },
    {
      "count": 2,
      "language": "VHDL"
    },
    {
      "count": 2,
      "language": "OpenSCAD"
    },
    {
      "count": 2,
      "language": "Smarty"
    },
    {
      "count": 2,
      "language": "NetLogo"
    },
    {
      "count": 2,
      "language": "Hy"
    },
    {
      "count": 1,
      "language": "AGS Script"
    },
    {
      "count": 1,
      "language": "Assembly"
    },
    {
      "count": 1,
      "language": "Mako"
    },
    {
      "count": 1,
      "language": "nesC"
    },
    {
      "count": 1,
      "language": "Ada"
    },
    {
      "count": 1,
      "language": "HaXe"
    },
    {
      "count": 1,
      "language": "BitBake"
    },
    {
      "count": 1,
      "language": "Squirrel"
    },
    {
      "count": 1,
      "language": "LoomScript"
    },
    {
      "count": 1,
      "language": "Pascal"
    },
    {
      "count": 1,
      "language": "Cuda"
    },
    {
      "count": 1,
      "language": "Stata"
    },
    {
      "count": 1,
      "language": "REALbasic"
    },
    {
      "count": 1,
      "language": "Hack"
    },
    {
      "count": 1,
      "language": "Modelica"
    },
    {
      "count": 1,
      "language": "M"
    },
    {
      "count": 1,
      "language": "Gnuplot"
    },
    {
      "count": 1,
      "language": "AutoIt"
    }
  ]
}
