{
  "files_processed": 24,
  "languages": [
    {
      "count": 14235,
      "language": "JavaScript"
    },
    {
      "count": 7400,
      "language": "Python"
    },
    {
      "count": 7302,
      "language": "Java"
    },
    {
      "count": 5598,
      "language": "Ruby"
    },
    {
      "count": 4521,
      "language": "HTML"
    },
    {
      "count": 3700,
      "language": "PHP"
    },
    {
      "count": 2965,
      "language": "C++"
    },
    {
      "count": 2261,
      "language": "CSS"
    },
    {
      "count": 2222,
      "language": "C#"
    },
    {
      "count": 2013,
      "language": "Go"
    },
    {
      "count": 1661,
      "language": "C"
    },
    {
      "count": 1284,
      "language": "Shell"
    },
    {
      "count": 1086,
      "language": "TypeScript"
    },
    {
      "count": 710,
      "language": "Scala"
    },
    {
      "count": 618,
      "language": "Swift"
    },
    {
      "count": 439,
      "language": "Objective-C"
    },
    {
      "count": 311,
      "language": "CoffeeScript"
    },
    {
      "count": 305,
      "language": "PowerShell"
    },
    {
      "count": 285,
      "language": "Perl"
    },
    {
      "count": 280,
      "language": "R"
    },
    {
      "count": 262,
      "language": "Jupyter Notebook"
    },
    {
      "count": 235,
      "language": "Rust"
    },
    {
      "count": 208,
      "language": "Makefile"
    },
    {
      "count": 176,
      "language": "Lua"
    },
    {
      "count": 170,
      "language": "Matlab"
    },
    {
      "count": 163,
      "language": "Clojure"
    },
    {
      "count": 146,
      "language": "TeX"
    },
    {
      "count": 136,
      "language": "Elixir"
    },
    {
      "count": 130,
      "language": "Groovy"
    },
    {
      "count": 118,
      "language": "Erlang"
    },
    {
      "count": 104,
      "language": "PLpgSQL"
    },
    {
      "count": 99,
      "language": "Haskell"
    },
    {
      "count": 88,
      "language": "GCC Machine Description"
    },
    {
      "count": 87,
      "language": "DM"
    },
    {
      "count": 80,
      "language": "VimL"
    },
    {
      "count": 80,
      "language": "OCaml"
    },
    {
      "count": 75,
      "language": "Julia"
    },
    {
      "count": 72,
      "language": "Puppet"
    },
    {
      "count": 72,
      "language": "Dart"
    },
    {
      "count": 56,
      "language": "Vue"
    },
    {
      "count": 53,
      "language": "CMake"
    },
    {
      "count": 51,
      "language": "XSLT"
    },
    {
      "count": 51,
      "language": "Arduino"
    },
    {
      "count": 49,
      "language": "Nix"
    },
    {
      "count": 48,
      "language": "Visual Basic"
    },
    {
      "count": 48,
      "language": "HCL"
    },
    {
      "count": 47,
      "language": "FORTRAN"
    },
    {
      "count": 46,
      "language": "MAXScript"
    },
    {
      "count": 45,
      "language": "Assembly"
    },
    {
      "count": 41,
      "language": "SaltStack"
    },
    {
      "count": 39,
      "language": "Batchfile"
    },
    {
      "count": 39,
      "language": "Haxe"
    },
    {
      "count": 37,
      "language": "SQF"
    },
    {
      "count": 37,
      "language": "Kotlin"
    },
    {
      "count": 37,
      "language": "Emacs Lisp"
    },
    {
      "count": 35,
      "language": "F#"
    },
    {
      "count": 35,
      "language": "Common Lisp"
    },
    {
      "count": 34,
      "language": "LiveScript"
    },
    {
      "count": 33,
      "language": "PLSQL"
    },
    {
      "count": 31,
      "language": "RobotFramework"
    },
    {
      "count": 30,
      "language": "Processing"
    },
    {
      "count": 30,
      "language": "Smarty"
    },
    {
      "count": 26,
      "language": "Pascal"
    },
    {
      "count": 26,
      "language": "Elm"
    },
    {
      "count": 25,
      "language": "Standard ML"
    },
    {
      "count": 21,
      "language": "ColdFusion"
    },
    {
      "count": 19,
      "language": "BitBake"
    },
    {
      "count": 19,
      "language": "FreeMarker"
    },
    {
      "count": 18,
      "language": "PureScript"
    },
    {
      "count": 17,
      "language": "PostScript"
    },
    {
      "count": 17,
      "language": "Eagle"
    },
    {
      "count": 17,
      "language": "QML"
    },
    {
      "count": 16,
      "language": "Groff"
    },
    {
      "count": 16,
      "language": "Modelica"
    },
    {
      "count": 15,
      "language": "Tcl"
    },
    {
      "count": 14,
      "language": "SQLPL"
    },
    {
      "count": 14,
      "language": "Prolog"
    },
    {
      "count": 13,
      "language": "Coq"
    },
    {
      "count": 13,
      "language": "Mathematica"
    },
    {
      "count": 13,
      "language": "RAML"
    },
    {
      "count": 13,
      "language": "ASP"
    },
    {
      "count": 12,
      "language": "Chapel"
    },
    {
      "count": 12,
      "language": "Crystal"
    },
    {
      "count": 10,
      "language": "D"
    },
    {
      "count": 10,
      "language": "GLSL"
    },
    {
      "count": 10,
      "language": "Nginx"
    },
    {
      "count": 9,
      "language": "Liquid"
    },
    {
      "count": 9,
      "language": "Protocol Buffer"
    },
    {
      "count": 9,
      "language": "Racket"
    },
    {
      "count": 9,
      "language": "OpenEdge ABL"
    },
    {
      "count": 9,
      "language": "NSIS"
    },
    {
      "count": 9,
      "language": "Scheme"
    },
    {
      "count": 8,
      "language": "Perl6"
    },
    {
      "count": 8,
      "language": "AGS Script"
    },
    {
      "count": 7,
      "language": "SourcePawn"
    },
    {
      "count": 7,
      "language": "Verilog"
    },
    {
      "count": 7,
      "language": "API Blueprint"
    },
    {
      "count": 7,
      "language": "Xtend"
    },
    {
      "count": 6,
      "language": "Apex"
    },
    {
      "count": 5,
      "language": "Web Ontology Language"
    },
    {
      "count": 5,
      "language": "1C Enterprise"
    },
    {
      "count": 5,
      "language": "Game Maker Language"
    },
    {
      "count": 5,
      "language": "Nimrod"
    },
    {
      "count": 4,
      "language": "Gnuplot"
    },
    {
      "count": 4,
      "language": "PAWN"
    },
    {
      "count": 4,
      "language": "GDScript"
    },
    {
      "count": 4,
      "language": "ooc"
    },
    {
      "count": 4,
      "language": "Cucumber"
    },
    {
      "count": 4,
      "language": "Objective-J"
    },
    {
      "count": 4,
      "language": "Slash"
    },
    {
      "count": 4,
      "language": "COBOL"
    },
    {
      "count": 4,
      "language": "Objective-C++"
    },
    {
      "count": 3,
      "language": "Logos"
    },
    {
      "count": 3,
      "language": "Shen"
    },
    {
      "count": 3,
      "language": "XQuery"
    },
    {
      "count": 3,
      "language": "Stan"
    },
    {
      "count": 3,
      "language": "Eiffel"
    },
    {
      "count": 3,
      "language": "ApacheConf"
    },
    {
      "count": 3,
      "language": "IDL"
    },
    {
      "count": 3,
      "language": "DIGITAL Command Language"
    },
    {
      "count": 3,
      "language": "GAP"
    },
    {
      "count": 3,
      "language": "Smalltalk"
    },
    {
      "count": 2,
      "language": "MQL5"
    },
    {
      "count": 2,
      "language": "KiCad"
    },
    {
      "count": 2,
      "language": "ABAP"
    },
    {
      "count": 2,
      "language": "Turing"
    },
    {
      "count": 2,
      "language": "AppleScript"
    },
    {
      "count": 2,
      "language": "Cuda"
    },
    {
      "count": 2,
      "language": "M"
    },
    {
      "count": 2,
      "language": "ActionScript"
    },
    {
      "count": 2,
      "language": "Gosu"
    },
    {
      "count": 2,
      "language": "LLVM"
    },
    {
      "count": 2,
      "language": "Limbo"
    },
    {
      "count": 2,
      "language": "IGOR Pro"
    },
    {
      "count": 2,
      "language": "Alloy"
    },
    {
      "count": 2,
      "language": "CartoCSS"
    },
    {
      "count": 2,
      "language": "Inform 7"
    },
    {
      "count": 2,
      "language": "VHDL"
    },
    {
      "count": 1,
      "language": "Pure Data"
    },
    {
      "count": 1,
      "language": "Bro"
    },
    {
      "count": 1,
      "language": "Ada"
    },
    {
      "count": 1,
      "language": "SuperCollider"
    },
    {
      "count": 1,
      "language": "HLSL"
    },
    {
      "count": 1,
      "language": "Hack"
    },
    {
      "count": 1,
      "language": "LOLCODE"
    },
    {
      "count": 1,
      "language": "ANTLR"
    },
    {
      "count": 1,
      "language": "LabVIEW"
    },
    {
      "count": 1,
      "language": "Augeas"
    },
    {
      "count": 1,
      "language": "Mako"
    },
    {
      "count": 1,
      "language": "SystemVerilog"
    },
    {
      "count": 1,
      "language": "Agda"
    },
    {
      "count": 1,
      "language": "Squirrel"
    },
    {
      "count": 1,
      "language": "LoomScript"
    },
    {
      "count": 1,
      "language": "Ren'Py"
    },
    {
      "count": 1,
      "language": "NetLogo"
    },
    {
      "count": 1,
      "language": "LilyPond"
    }
  ]
}
