{"events":{"CommitCommentEvent":1529,"CreateEvent":144808,"DeleteEvent":29728,"ForkEvent":24616,"GollumEvent":4655,"IssueCommentEvent":46918,"IssuesEvent":29691,"MemberEvent":3078,"PublicEvent":3100,"PullRequestEvent":48583,"PullRequestReviewCommentEvent":10751,"PushEvent":585354,"ReleaseEvent":3481,"WatchEvent":72726},"file_count":24,"hours":{"0":34397,"1":33644,"10":39404,"11":45977,"12":50404,"13":49201,"14":49553,"15":50785,"16":51230,"17":51173,"18":50916,"19":49603,"2":33430,"20":50486,"21":48313,"22":43919,"23":39364,"3":33669,"4":32132,"5":33662,"6":33239,"7":33361,"8":33891,"9":37265},"languages":{"ABAP":1,"AGS Script":1,"AMPL":3,"ASP":10,"Ada":2,"Agda":1,"Apex":6,"Arduino":6,"Assembly":25,"AutoIt":2,"Ballerina":1,"Batchfile":31,"BitBake":15,"Brainfuck":2,"C":990,"C#":3190,"C++":1960,"CMake":45,"CSS":1236,"CartoCSS":2,"Chapel":3,"ChucK":1,"Clojure":46,"CoffeeScript":24,"ColdFusion":4,"Common Lisp":8,"Coq":1,"Crystal":16,"D":25,"DIGITAL Command Language":2,"DM":248,"Dart":125,"Dockerfile":106,"Elixir":117,"Elm":17,"Emacs Lisp":52,"Erlang":22,"F#":22,"Forth":3,"Fortran":10,"FreeMarker":5,"GAP":7,"GCC Machine Description":2,"GDScript":87,"GLSL":1,"Game Maker Language":4,"Gherkin":4,"Gnuplot":5,"Go":1165,"Groovy":27,"HCL":54,"HTML":3906,"Hack":10,"Haskell":89,"Haxe":2,"Inform 7":2,"Inno Setup":1,"Java":3561,"JavaScript":9659,"Julia":112,"Jupyter Notebook":323,"Kotlin":335,"LSL":7,"LabVIEW":1,"Lean":15,"Liquid":3,"Lua":178,"M4":5,"MATLAB":26,"MQL4":4,"Makefile":219,"Mask":1,"Mathematica":10,"Matlab":6,"Max":2,"Modelica":1,"NCL":1,"NSIS":1,"NetLogo":3,"Nextflow":4,"Nim":24,"Nix":144,"OCaml":37,"Objective-C":70,"Objective-C++":4,"Objective-J":5,"OpenEdge ABL":1,"Oz":1,"PHP":1788,"PLSQL":28,"PLpgSQL":23,"Pascal":15,"Perl":61,"PostScript":4,"PowerShell":136,"Processing":43,"Prolog":3,"Puppet":9,"PureScript":1,"Python":4208,"QML":14,"R":150,"RAML":1,"REALbasic":3,"Racket":5,"Rascal":2,"Red":3,"Ren'Py":7,"RobotFramework":1,"Roff":19,"Ruby":2560,"Rust":473,"SAS":1,"SMT":1,"SQF":9,"SQLPL":4,"SaltStack":10,"Scala":193,"Scheme":14,"Scilab":4,"ShaderLab":166,"Shell":936,"Slice":2,"Smalltalk":18,"Smarty":24,"Solidity":9,"SourcePawn":3,"Standard ML":4,"Swift":361,"SystemVerilog":3,"Tcl":17,"TeX":149,"TypeScript":2008,"VCL":9,"VHDL":7,"Vala":33,"Verilog":10,"Vim script":67,"VimL":4,"Visual Basic":17,"Vue":406,"WebAssembly":10,"XQuery":4,"XSLT":35,"xBase":3}}
