{"events":{"CommitCommentEvent":12483,"CreateEvent":390404,"DeleteEvent":77966,"ForkEvent":37455,"GollumEvent":5440,"IssueCommentEvent":111011,"IssuesEvent":61740,"MemberEvent":11669,"PublicEvent":11061,"PullRequestEvent":191057,"PullRequestReviewCommentEvent":24464,"PullRequestReviewEvent":39252,"PushEvent":2237336,"ReleaseEvent":18038,"WatchEvent":155615},"file_count":24,"hours":{"0":158164,"1":148691,"10":135939,"11":136964,"12":208200,"13":173670,"14":160456,"15":164978,"16":164087,"17":152451,"18":152767,"19":143496,"2":113745,"20":139808,"21":130444,"22":126256,"23":119599,"3":111460,"4":112863,"5":116480,"6":124657,"7":122823,"8":131734,"9":135259},"languages":{"1C Enterprise":3,"ABAP":7,"AGS Script":6,"AMPL":6,"ANTLR":10,"ASL":2,"ASP.NET":1,"ActionScript":4,"Ada":9,"Adblock Filter List":54,"Agda":4,"AngelScript":12,"Apex":32,"Arduino":1,"Assembly":56,"Astro":346,"AutoHotkey":11,"AutoIt":3,"Awk":2,"BASIC":7,"Ballerina":28,"Batchfile":91,"Beef":2,"Bicep":29,"Bikeshed":5,"BitBake":18,"Blade":272,"BlitzMax":7,"BrighterScript":5,"Brightscript":1,"C":3180,"C#":8134,"C++":5349,"CMake":98,"CSS":2630,"CUE":8,"CWeb":1,"Cairo":16,"CartoCSS":1,"Chapel":1,"Circom":1,"Clarity":2,"Classic ASP":3,"Clojure":109,"CodeQL":2,"CoffeeScript":14,"ColdFusion":3,"Common Lisp":32,"Common Workflow Language":2,"Coq":17,"Crystal":29,"Cuda":14,"Cython":4,"D":16,"DIGITAL Command Language":6,"DM":449,"DTrace":1,"Dart":1701,"Dockerfile":1044,"Dylan":1,"EJS":308,"Earthly":2,"Elixir":213,"Elm":19,"Emacs Lisp":67,"Erlang":51,"F#":92,"F*":4,"Fluent":10,"Fortran":59,"FreeMarker":7,"G-code":8,"GAP":4,"GDScript":216,"GLSL":12,"Game Maker Language":4,"Gherkin":9,"Gleam":2,"Go":7316,"Groovy":77,"HCL":1610,"HLSL":11,"HTML":9407,"Hack":26,"Haml":1,"Handlebars":64,"Haskell":170,"Haxe":23,"Idris":4,"Inno Setup":4,"JSON":5,"Janet":4,"Java":13478,"JavaScript":25678,"Jinja":1021,"Jsonnet":20,"Julia":287,"Jupyter Notebook":1978,"Just":42,"Kaitai Struct":1,"KerboScript":2,"Kotlin":2920,"LLVM":6,"LabVIEW":4,"Lasso":5,"Latte":1,"Lean":93,"Less":67,"Lex":2,"Liquid":29,"Logos":1,"Lua":748,"M":2,"M4":4,"MATLAB":45,"MAXScript":1,"MDX":371,"MLIR":10,"Macaulay2":1,"Makefile":372,"Markdown":145,"Mathematica":16,"Max":2,"Meson":5,"Metal":4,"Modelica":6,"Monkey C":2,"MoonScript":2,"Motoko":6,"Move":6,"Mustache":54,"NWScript":4,"Nextflow":9,"Nim":32,"Nix":802,"Nunjucks":27,"Nushell":21,"OCaml":96,"Objective-C":50,"Objective-C++":3,"Odin":5,"Open Policy Agent":22,"OpenQASM":2,"OpenSCAD":8,"PEG.js":1,"PHP":4392,"PLSQL":9,"PLpgSQL":52,"Papyrus":4,"Pascal":67,"Pawn":1,"Perl":119,"PowerShell":387,"Processing":6,"Prolog":9,"Pug":10,"PureBasic":4,"PureScript":2,"Python":19061,"QML":30,"R":332,"RAML":4,"RPM Spec":11,"Racket":16,"Raku":1,"ReScript":26,"Reason":3,"Red":2,"Ren'Py":18,"RenderScript":8,"Rich Text Format":55,"RobotFramework":4,"Roff":718,"RouterOS Script":5,"Ruby":2373,"Rust":3466,"SCSS":836,"SMT":6,"SQF":19,"SQL":5,"SaltStack":4,"Sass":10,"Scala":1306,"Scheme":34,"Scilab":2,"ShaderLab":309,"Shell":3948,"Smalltalk":19,"Smarty":872,"Solidity":348,"SourcePawn":3,"Squirrel":7,"Standard ML":2,"Starlark":550,"Stata":3,"Stylus":10,"SuperCollider":6,"Svelte":587,"Swift":1089,"SystemVerilog":26,"TSQL":19,"Tcl":39,"TeX":268,"Text":12,"Twig":13,"TypeScript":30019,"Typst":22,"UnrealScript":4,"V":44,"VBScript":3,"VHDL":15,"Vala":7,"Verilog":33,"Vim Script":55,"Vim Snippet":4,"Vim script":1,"VimL":2,"Visual Basic .NET":24,"Visual Basic 6.0":1,"Vue":1997,"WGSL":2,"WebAssembly":6,"Witcher Script":6,"XML":6,"XQuery":1,"XSLT":15,"Xtend":2,"YAML":118,"YARA":4,"YASnippet":1,"Yacc":17,"ZenScript":10,"Zig":52,"hoon":2,"kvlang":1,"mcfunction":7,"nesC":6,"reStructuredText":55,"sed":4}}
