{"events":{"CommitCommentEvent":5164,"CreateEvent":763498,"DeleteEvent":278020,"ForkEvent":55425,"GollumEvent":7873,"IssueCommentEvent":221624,"IssuesEvent":89125,"MemberEvent":17641,"PublicEvent":17732,"PullRequestEvent":334974,"PullRequestReviewCommentEvent":80773,"PullRequestReviewEvent":141316,"PushEvent":3620497,"ReleaseEvent":25722,"WatchEvent":240391},"file_count":24,"hours":{"0":237066,"1":228163,"10":255630,"11":252447,"12":302497,"13":281218,"14":280367,"15":279775,"16":277450,"17":272613,"18":275235,"19":260997,"2":200471,"20":258400,"21":239740,"22":227490,"23":217319,"3":199636,"4":190668,"5":203095,"6":229712,"7":229203,"8":243405,"9":257178},"languages":{"1C Enterprise":8,"ABAP":6,"AGS Script":4,"AL":20,"AMPL":8,"ANTLR":6,"API Blueprint":10,"ASL":37,"ASP.NET":32,"ActionScript":1,"Ada":6,"Adblock Filter List":74,"Agda":12,"AngelScript":3,"Apex":172,"AppleScript":1,"Arc":1,"Arduino":1,"AsciiDoc":10,"Assembly":96,"Astro":933,"AutoHotkey":8,"AutoIt":1,"Awk":1,"Ballerina":57,"Batchfile":117,"Bicep":89,"Bikeshed":20,"BitBake":28,"Blade":410,"Bluespec":2,"Boogie":4,"Brainfuck":41,"BrighterScript":2,"Brightscript":1,"C":4534,"C#":11474,"C++":9674,"CAP CDS":64,"CMake":213,"COBOL":7,"CSS":3986,"CUE":34,"CWeb":2,"Cadence":5,"Cairo":32,"CartoCSS":2,"Chapel":28,"Cirru":1,"Clarity":1,"Classic ASP":2,"Clean":6,"Clojure":245,"CodeQL":38,"CoffeeScript":75,"ColdFusion":14,"Common Lisp":31,"Common Workflow Language":5,"Coq":17,"Crystal":26,"Cuda":32,"Cython":19,"D":13,"D2":3,"DIGITAL Command Language":16,"DM":445,"DTrace":8,"Dafny":5,"Dart":2130,"DenizenScript":3,"Dhall":2,"Dockerfile":2292,"Dylan":2,"EJS":295,"Earthly":6,"EdgeQL":2,"Eiffel":1,"Elixir":703,"Elm":49,"Emacs Lisp":107,"EmberScript":1,"Erlang":70,"Euphoria":2,"F#":97,"F*":3,"FORTRAN":2,"Fennel":3,"Fluent":17,"Forth":1,"Fortran":182,"FreeMarker":16,"G-code":9,"GAMS":1,"GAP":5,"GDScript":238,"GLSL":89,"Game Maker Language":5,"Gherkin":55,"Gleam":9,"Go":22086,"Grammatical Framework":1,"Groovy":196,"HCL":4288,"HLSL":5,"HTML":14529,"Hack":95,"Handlebars":97,"Haskell":218,"Haxe":23,"HolyC":1,"IGOR Pro":2,"Idris":2,"Inno Setup":3,"JSON":54,"Jasmin":2,"Java":23666,"JavaScript":42076,"JetBrains MPS":6,"Jinja":481,"Jsonnet":70,"Julia":643,"Jupyter Notebook":3725,"Just":15,"KerboScript":1,"Kotlin":5213,"LFE":1,"LLVM":29,"LabVIEW":6,"Lean":70,"Less":38,"Lex":1,"LilyPond":4,"Liquid":90,"Logos":3,"LookML":10,"Lua":904,"M":2,"M4":11,"MATLAB":119,"MDX":1053,"MLIR":33,"Makefile":896,"Markdown":1245,"Marko":10,"Mathematica":43,"Max":4,"Mermaid":37,"Meson":1,"Modelica":24,"Monkey C":4,"Motoko":4,"Move":21,"Mustache":379,"NASL":2,"NSIS":4,"NWScript":2,"Nasal":1,"Nextflow":83,"Nim":58,"Nix":1117,"Nunjucks":124,"Nushell":30,"OCaml":148,"ObjectScript":6,"Objective-C":151,"Objective-C++":19,"Odin":6,"Open Policy Agent":79,"OpenEdge ABL":2,"OpenSCAD":17,"P4":4,"PDDL":3,"PEG.js":1,"PHP":7820,"PLSQL":22,"PLpgSQL":234,"Pascal":55,"Pawn":6,"Perl":230,"Pony":3,"Portugol":1,"PostScript":10,"PowerShell":810,"Processing":65,"Procfile":2,"Prolog":7,"Pug":45,"Puppet":18,"PureBasic":2,"PureScript":20,"Python":36308,"QML":32,"QMake":2,"R":781,"RPGLE":2,"RPM Spec":29,"Racket":23,"Raku":2,"ReScript":18,"Reason":2,"Ren'Py":15,"Rez":1,"Rich Text Format":78,"RobotFramework":85,"Roff":305,"RouterOS Script":9,"Ruby":6336,"Rust":8670,"SAS":6,"SCSS":1530,"SMT":14,"SQF":20,"SQL":5,"SWIG":5,"Sage":8,"SaltStack":10,"Sass":16,"Scala":1904,"Scheme":24,"Scilab":2,"ShaderLab":325,"Shell":6776,"Slim":8,"Smalltalk":62,"Smarty":1155,"Smithy":2,"Solidity":479,"SourcePawn":27,"Squirrel":12,"Stan":3,"Standard ML":10,"Starlark":620,"Stata":21,"Stylus":18,"Svelte":1142,"Swift":2057,"SystemVerilog":68,"TLA":4,"TSQL":75,"Tcl":29,"TeX":391,"Text":8,"Thrift":2,"Toit":34,"Twig":116,"TypeScript":55289,"Typst":12,"UnrealScript":4,"UrWeb":1,"V":7,"VBA":2,"VBScript":4,"VHDL":25,"Vala":26,"Valve Data Format":1,"Velocity Template Language":3,"Verilog":69,"Vim Script":131,"Vim script":3,"Visual Basic .NET":28,"Visual Basic 6.0":39,"Vue":2916,"Vyper":1,"WDL":8,"WebAssembly":23,"Witcher Script":3,"Wren":1,"XC":2,"XML":11,"XQuery":4,"XS":10,"XSLT":61,"Xtend":11,"YAML":216,"YARA":16,"YASnippet":2,"Yacc":24,"Zeek":5,"ZenScript":6,"Zig":107,"jq":2,"kvlang":1,"mIRC Script":14,"mcfunction":5,"nesC":8,"q":2,"reStructuredText":42,"sed":1}}
